Metadata-Version: 2.1
Name: cz-github-jira-conventional-footer
Version: 1.0.2
Summary: Extend the commitizen tools to create conventional commits and changelog that link to Jira and GitHub.
Home-page: https://github.com/brianburwell11/cz-github-jira-conventional-footer
Author: Brian Burwell
Author-email: brianburwell11@gmail.com
License: MIT
Platform: UNKNOWN
License-File: LICENSE
